metaai_compiler/__init__.py
metaai_compiler/__version__.py
metaai_compiler/main.py
metaai_compiler-0.1.8.dist-info/entry_points.txt
metaai_compiler-0.1.8.dist-info/WHEEL
metaai_compiler-0.1.8.dist-info/METADATA
metaai_compiler-0.1.8.dist-info/RECORD
